chunk_logger/__init__.py
chunk_logger-1.0.0.dist-info/LICENSE
chunk_logger-1.0.0.dist-info/METADATA
chunk_logger-1.0.0.dist-info/WHEEL
chunk_logger-1.0.0.dist-info/top_level.txt
chunk_logger-1.0.0.dist-info/RECORD
